Reviews/CSVReviewsWriter.py
Reviews/DefaultDataConverter.py
Reviews/IDataConverter.py
Reviews/IReviewsWriter.py
Reviews/ReviewsLoader.py
Reviews/TaskIterator.py
Reviews/__init__.py
Reviews/__main__.py
ReviewsLoader-0.1.dist-info/LICENSE.txt
ReviewsLoader-0.1.dist-info/METADATA
ReviewsLoader-0.1.dist-info/WHEEL
ReviewsLoader-0.1.dist-info/top_level.txt
ReviewsLoader-0.1.dist-info/RECORD
