Metadata-Version: 2.1
Name: ReviewsLoader
Version: 0.1
Summary: Utility for downloading app reviews in the App Store.
Home-page: https://gitlab.com/maksimvrs/reviewsloader
Author: Maksim Vorontsov
Author-email: social.maksim.vrs@gmail.com
License: MIT
Download-URL: https://gitlab.com/maksimvrs/reviewsloader/-/archive/master/reviewsloader-master.tar.gz
Keywords: parser,AppStore,async
Platform: UNKNOWN
Classifier: Development Status :: 3 - Alpha
Classifier: Intended Audience :: Developers
Classifier: Topic :: Software Development :: Build Tools
Classifier: License :: OSI Approved :: MIT License
Classifier: Programming Language :: Python :: 3
Classifier: Programming Language :: Python :: 3.4
Classifier: Programming Language :: Python :: 3.5
Classifier: Programming Language :: Python :: 3.6
Classifier: Programming Language :: Python :: 3.7
Classifier: Programming Language :: Python :: 3.8
Requires-Dist: aioify
Requires-Dist: aiohttp
Requires-Dist: click
